{"f1": 0.3609022556390977, "f1_macro": 0.38984355743325216, "precision": 0.3526608419380461, "recall": 0.36953807740324596, "accuracy": 0.029814665592264304, "threshold": 0.35, "label_scores": {"MT": {"precision": 0.0, "recall": 0.0, "f1-score": 0.0, "support": 64.0}, "LY": {"precision": 0.0, "recall": 0.0, "f1-score": 0.0, "support": 13.0}, "SP": {"precision": 0.0, "recall": 0.0, "f1-score": 0.0, "support": 15.0}, "ID": {"precision": 0.0, "recall": 0.0, "f1-score": 0.0, "support": 120.0}, "NA": {"precision": 0.38130563798219586, "recall": 0.7907692307692308, "f1-score": 0.5145145145145146, "support": 325.0}, "HI": {"precision": 0.0, "recall": 0.0, "f1-score": 0.0, "support": 72.0}, "IN": {"precision": 0.3498542274052478, "recall": 0.75, "f1-score": 0.4771371769383697, "support": 320.0}, "OP": {"precision": 0.0, "recall": 0.0, "f1-score": 0.0, "support": 150.0}, "IP": {"precision": 0.3345008756567426, "recall": 0.9820051413881749, "f1-score": 0.4990202482037884, "support": 389.0}, "it": {"precision": 0.0, "recall": 0.0, "f1-score": 0.0, "support": 8.0}, "ne": {"precision": 0.0, "recall": 0.0, "f1-score": 0.0, "support": 124.0}, "sr": {"precision": 0.0, "recall": 0.0, "f1-score": 0.0, "support": 23.0}, "nb": {"precision": 0.0, "recall": 0.0, "f1-score": 0.0, "support": 128.0}, "re": {"precision": 0.0, "recall": 0.0, "f1-score": 0.0, "support": 21.0}, "en": {"precision": 0.0, "recall": 0.0, "f1-score": 0.0, "support": 34.0}, "ra": {"precision": 0.0, "recall": 0.0, "f1-score": 0.0, "support": 10.0}, "dtp": {"precision": 0.0, "recall": 0.0, "f1-score": 0.0, "support": 149.0}, "fi": {"precision": 0.0, "recall": 0.0, "f1-score": 0.0, "support": 6.0}, "lt": {"precision": 0.0, "recall": 0.0, "f1-score": 0.0, "support": 38.0}, "rv": {"precision": 0.0, "recall": 0.0, "f1-score": 0.0, "support": 76.0}, "ob": {"precision": 0.0, "recall": 0.0, "f1-score": 0.0, "support": 27.0}, "rs": {"precision": 0.0, "recall": 0.0, "f1-score": 0.0, "support": 7.0}, "av": {"precision": 0.0, "recall": 0.0, "f1-score": 0.0, "support": 28.0}, "ds": {"precision": 0.5625, "recall": 0.036585365853658534, "f1-score": 0.06870229007633587, "support": 246.0}, "ed": {"precision": 0.0, "recall": 0.0, "f1-score": 0.0, "support": 10.0}}}