{"f1": 0.6778846153846154, "precision": 0.698019801980198, "recall": 0.6588785046728972, "accuracy": 0.4879518072289157, "pr_auc": 0.7164716356186968, "threshold": 0.44999999999999996, "label_scores": {"MT": {"precision": 0.0, "recall": 0.0, "f1-score": 0.0, "support": 0.0}, "LY": {"precision": 0.0, "recall": 0.0, "f1-score": 0.0, "support": 4.0}, "SP": {"precision": 0.0, "recall": 0.0, "f1-score": 0.0, "support": 0.0}, "ID": {"precision": 0.6666666666666666, "recall": 0.23529411764705882, "f1-score": 0.3478260869565218, "support": 17.0}, "NA": {"precision": 0.7984496124031008, "recall": 0.911504424778761, "f1-score": 0.8512396694214877, "support": 113.0}, "HI": {"precision": 0.8125, "recall": 0.40625, "f1-score": 0.5416666666666666, "support": 32.0}, "IN": {"precision": 0.4861111111111111, "recall": 0.6363636363636364, "f1-score": 0.5511811023622047, "support": 55.0}, "OP": {"precision": 0.5833333333333334, "recall": 0.4666666666666667, "f1-score": 0.5185185185185186, "support": 30.0}, "IP": {"precision": 0.8217821782178217, "recall": 0.7345132743362832, "f1-score": 0.7757009345794393, "support": 113.0}, "it": {"precision": 0.0, "recall": 0.0, "f1-score": 0.0, "support": 0.0}, "ne": {"precision": 0.6875, "recall": 0.88, "f1-score": 0.7719298245614036, "support": 75.0}, "sr": {"precision": 0.6, "recall": 0.5, "f1-score": 0.5454545454545454, "support": 6.0}, "nb": {"precision": 0.4166666666666667, "recall": 0.2631578947368421, "f1-score": 0.3225806451612903, "support": 19.0}, "re": {"precision": 1.0, "recall": 0.8333333333333334, "f1-score": 0.9090909090909091, "support": 6.0}, "en": {"precision": 0.0, "recall": 0.0, "f1-score": 0.0, "support": 3.0}, "ra": {"precision": 0.0, "recall": 0.0, "f1-score": 0.0, "support": 2.0}, "dtp": {"precision": 0.125, "recall": 0.15789473684210525, "f1-score": 0.13953488372093023, "support": 19.0}, "fi": {"precision": 0.0, "recall": 0.0, "f1-score": 0.0, "support": 1.0}, "lt": {"precision": 0.5, "recall": 0.625, "f1-score": 0.5555555555555556, "support": 8.0}, "rv": {"precision": 1.0, "recall": 0.2222222222222222, "f1-score": 0.3636363636363636, "support": 9.0}, "ob": {"precision": 0.0, "recall": 0.0, "f1-score": 0.0, "support": 5.0}, "rs": {"precision": 0.875, "recall": 0.7777777777777778, "f1-score": 0.823529411764706, "support": 9.0}, "av": {"precision": 0.0, "recall": 0.0, "f1-score": 0.0, "support": 6.0}, "ds": {"precision": 0.872093023255814, "recall": 0.7075471698113207, "f1-score": 0.7812499999999999, "support": 106.0}, "ed": {"precision": 0.0, "recall": 0.0, "f1-score": 0.0, "support": 4.0}}}